{"config":{"output_file":null,"full_docs":false,"pub_only":true,"reachable_only":true,"distro_crate":false,"signatures":false,"borrow_data":false},"version":"0.19.1","compilation":{"directory":"/home/d33p/.cargo/registry/src/github.com-1ecc6299db9ec823/panic-itm-0.4.2","program":"/home/d33p/.rustup/toolchains/stable-x86_64-unknown-linux-gnu/bin/rls","arguments":["--crate-name","panic_itm","/home/d33p/.cargo/registry/src/github.com-1ecc6299db9ec823/panic-itm-0.4.2/src/lib.rs","--json=diagnostic-rendered-ansi","--crate-type","lib","--emit=dep-info,metadata","-C","embed-bitcode=no","-C","debuginfo=2","-C","metadata=c56b2b8c498b72b0","-C","extra-filename=-c56b2b8c498b72b0","--out-dir","/home/d33p/dev/BareMetal/baremetal-embedded/led_toggle_0/led_toggle_rust_0/target/rls/thumbv7em-none-eabihf/debug/deps","--target","thumbv7em-none-eabihf","-L","dependency=/home/d33p/dev/BareMetal/baremetal-embedded/led_toggle_0/led_toggle_rust_0/target/rls/thumbv7em-none-eabihf/debug/deps","-L","dependency=/home/d33p/dev/BareMetal/baremetal-embedded/led_toggle_0/led_toggle_rust_0/target/rls/debug/deps","--extern","cortex_m=/home/d33p/dev/BareMetal/baremetal-embedded/led_toggle_0/led_toggle_rust_0/target/rls/thumbv7em-none-eabihf/debug/deps/libcortex_m-621e8b4e529dda11.rmeta","--cap-lints","allow","-L","/home/d33p/dev/BareMetal/baremetal-embedded/led_toggle_0/led_toggle_rust_0/target/rls/thumbv7em-none-eabihf/debug/build/cortex-m-d1c01c9da6b40276/out","--error-format=json","--sysroot","/home/d33p/.rustup/toolchains/stable-x86_64-unknown-linux-gnu"],"output":"/home/d33p/dev/BareMetal/baremetal-embedded/led_toggle_0/led_toggle_rust_0/target/rls/thumbv7em-none-eabihf/debug/deps/libpanic_itm-c56b2b8c498b72b0.rmeta"},"prelude":{"crate_id":{"name":"panic_itm","disambiguator":[2016573476647201344,1292238898441441043]},"crate_root":"/home/d33p/.cargo/registry/src/github.com-1ecc6299db9ec823/panic-itm-0.4.2/src","external_crates":[{"file_name":"/home/d33p/.cargo/registry/src/github.com-1ecc6299db9ec823/panic-itm-0.4.2/src/lib.rs","num":1,"id":{"name":"core","disambiguator":[2184632775997829466,18026496178680965583]}},{"file_name":"/home/d33p/.cargo/registry/src/github.com-1ecc6299db9ec823/panic-itm-0.4.2/src/lib.rs","num":2,"id":{"name":"compiler_builtins","disambiguator":[3726307931522043477,4911878782996857177]}},{"file_name":"/home/d33p/.cargo/registry/src/github.com-1ecc6299db9ec823/panic-itm-0.4.2/src/lib.rs","num":3,"id":{"name":"rustc_std_workspace_core","disambiguator":[8506066526834043935,2338947288633172727]}},{"file_name":"/home/d33p/.cargo/registry/src/github.com-1ecc6299db9ec823/panic-itm-0.4.2/src/lib.rs","num":4,"id":{"name":"cortex_m","disambiguator":[640354376001017179,674240275051986860]}},{"file_name":"/home/d33p/.cargo/registry/src/github.com-1ecc6299db9ec823/panic-itm-0.4.2/src/lib.rs","num":5,"id":{"name":"bare_metal","disambiguator":[4564207712410018107,9487563642666486471]}},{"file_name":"/home/d33p/.cargo/registry/src/github.com-1ecc6299db9ec823/panic-itm-0.4.2/src/lib.rs","num":6,"id":{"name":"volatile_register","disambiguator":[12924141464269962721,11423500608467426660]}},{"file_name":"/home/d33p/.cargo/registry/src/github.com-1ecc6299db9ec823/panic-itm-0.4.2/src/lib.rs","num":7,"id":{"name":"vcell","disambiguator":[13115093308910904468,13284027448544462362]}},{"file_name":"/home/d33p/.cargo/registry/src/github.com-1ecc6299db9ec823/panic-itm-0.4.2/src/lib.rs","num":8,"id":{"name":"embedded_hal","disambiguator":[11190912420879959913,7761254619970545346]}},{"file_name":"/home/d33p/.cargo/registry/src/github.com-1ecc6299db9ec823/panic-itm-0.4.2/src/lib.rs","num":9,"id":{"name":"nb","disambiguator":[15401273450865999483,13772608842728756265]}},{"file_name":"/home/d33p/.cargo/registry/src/github.com-1ecc6299db9ec823/panic-itm-0.4.2/src/lib.rs","num":10,"id":{"name":"nb","disambiguator":[15010377001352867217,15689185407496902103]}},{"file_name":"/home/d33p/.cargo/registry/src/github.com-1ecc6299db9ec823/panic-itm-0.4.2/src/lib.rs","num":11,"id":{"name":"void","disambiguator":[13969028487453651476,12471677446926910835]}}],"span":{"file_name":"/home/d33p/.cargo/registry/src/github.com-1ecc6299db9ec823/panic-itm-0.4.2/src/lib.rs","byte_start":0,"byte_end":1420,"line_start":1,"line_end":59,"column_start":1,"column_end":2}},"imports":[],"defs":[{"kind":"Mod","id":{"krate":0,"index":0},"span":{"file_name":"/home/d33p/.cargo/registry/src/github.com-1ecc6299db9ec823/panic-itm-0.4.2/src/lib.rs","byte_start":0,"byte_end":1420,"line_start":1,"line_end":59,"column_start":1,"column_end":2},"name":"","qualname":"::","value":"/home/d33p/.cargo/registry/src/github.com-1ecc6299db9ec823/panic-itm-0.4.2/src/lib.rs","parent":null,"children":[{"krate":0,"index":1},{"krate":0,"index":2},{"krate":0,"index":3},{"krate":0,"index":4},{"krate":0,"index":5},{"krate":0,"index":6},{"krate":0,"index":7},{"krate":0,"index":8},{"krate":0,"index":9},{"krate":0,"index":10},{"krate":0,"index":11},{"krate":0,"index":12}],"decl_id":null,"docs":" Log panic messages using the ITM (Instrumentation Trace Macrocell)","sig":null,"attributes":[{"value":"/ Log panic messages using the ITM (Instrumentation Trace Macrocell)","span":{"file_name":"/home/d33p/.cargo/registry/src/github.com-1ecc6299db9ec823/panic-itm-0.4.2/src/lib.rs","byte_start":0,"byte_end":70,"line_start":1,"line_end":1,"column_start":1,"column_end":71}},{"value":"/","span":{"file_name":"/home/d33p/.cargo/registry/src/github.com-1ecc6299db9ec823/panic-itm-0.4.2/src/lib.rs","byte_start":71,"byte_end":74,"line_start":2,"line_end":2,"column_start":1,"column_end":4}},{"value":"/ This crate contains an implementation of `panic_fmt` that logs panic messages to the ITM","span":{"file_name":"/home/d33p/.cargo/registry/src/github.com-1ecc6299db9ec823/panic-itm-0.4.2/src/lib.rs","byte_start":75,"byte_end":167,"line_start":3,"line_end":3,"column_start":1,"column_end":93}},{"value":"/ stimulus port 0. Before printing the message the panic handler disables (masks) all the device","span":{"file_name":"/home/d33p/.cargo/registry/src/github.com-1ecc6299db9ec823/panic-itm-0.4.2/src/lib.rs","byte_start":168,"byte_end":266,"line_start":4,"line_end":4,"column_start":1,"column_end":99}},{"value":"/ specific interrupts. After printing the message the panic handler goes into an infinite loop.","span":{"file_name":"/home/d33p/.cargo/registry/src/github.com-1ecc6299db9ec823/panic-itm-0.4.2/src/lib.rs","byte_start":267,"byte_end":364,"line_start":5,"line_end":5,"column_start":1,"column_end":98}},{"value":"/","span":{"file_name":"/home/d33p/.cargo/registry/src/github.com-1ecc6299db9ec823/panic-itm-0.4.2/src/lib.rs","byte_start":365,"byte_end":368,"line_start":6,"line_end":6,"column_start":1,"column_end":4}},{"value":"/ # Usage","span":{"file_name":"/home/d33p/.cargo/registry/src/github.com-1ecc6299db9ec823/panic-itm-0.4.2/src/lib.rs","byte_start":369,"byte_end":380,"line_start":7,"line_end":7,"column_start":1,"column_end":12}},{"value":"/","span":{"file_name":"/home/d33p/.cargo/registry/src/github.com-1ecc6299db9ec823/panic-itm-0.4.2/src/lib.rs","byte_start":381,"byte_end":384,"line_start":8,"line_end":8,"column_start":1,"column_end":4}},{"value":"/ ``` ignore","span":{"file_name":"/home/d33p/.cargo/registry/src/github.com-1ecc6299db9ec823/panic-itm-0.4.2/src/lib.rs","byte_start":385,"byte_end":399,"line_start":9,"line_end":9,"column_start":1,"column_end":15}},{"value":"/ #![no_std]","span":{"file_name":"/home/d33p/.cargo/registry/src/github.com-1ecc6299db9ec823/panic-itm-0.4.2/src/lib.rs","byte_start":400,"byte_end":414,"line_start":10,"line_end":10,"column_start":1,"column_end":15}},{"value":"/","span":{"file_name":"/home/d33p/.cargo/registry/src/github.com-1ecc6299db9ec823/panic-itm-0.4.2/src/lib.rs","byte_start":415,"byte_end":418,"line_start":11,"line_end":11,"column_start":1,"column_end":4}},{"value":"/ extern crate panic_itm;","span":{"file_name":"/home/d33p/.cargo/registry/src/github.com-1ecc6299db9ec823/panic-itm-0.4.2/src/lib.rs","byte_start":419,"byte_end":446,"line_start":12,"line_end":12,"column_start":1,"column_end":28}},{"value":"/","span":{"file_name":"/home/d33p/.cargo/registry/src/github.com-1ecc6299db9ec823/panic-itm-0.4.2/src/lib.rs","byte_start":447,"byte_end":450,"line_start":13,"line_end":13,"column_start":1,"column_end":4}},{"value":"/ fn main() {","span":{"file_name":"/home/d33p/.cargo/registry/src/github.com-1ecc6299db9ec823/panic-itm-0.4.2/src/lib.rs","byte_start":451,"byte_end":466,"line_start":14,"line_end":14,"column_start":1,"column_end":16}},{"value":"/     panic!(\"FOO\")","span":{"file_name":"/home/d33p/.cargo/registry/src/github.com-1ecc6299db9ec823/panic-itm-0.4.2/src/lib.rs","byte_start":467,"byte_end":488,"line_start":15,"line_end":15,"column_start":1,"column_end":22}},{"value":"/ }","span":{"file_name":"/home/d33p/.cargo/registry/src/github.com-1ecc6299db9ec823/panic-itm-0.4.2/src/lib.rs","byte_start":489,"byte_end":494,"line_start":16,"line_end":16,"column_start":1,"column_end":6}},{"value":"/ ```","span":{"file_name":"/home/d33p/.cargo/registry/src/github.com-1ecc6299db9ec823/panic-itm-0.4.2/src/lib.rs","byte_start":495,"byte_end":502,"line_start":17,"line_end":17,"column_start":1,"column_end":8}},{"value":"/","span":{"file_name":"/home/d33p/.cargo/registry/src/github.com-1ecc6299db9ec823/panic-itm-0.4.2/src/lib.rs","byte_start":503,"byte_end":506,"line_start":18,"line_end":18,"column_start":1,"column_end":4}},{"value":"/ ``` text","span":{"file_name":"/home/d33p/.cargo/registry/src/github.com-1ecc6299db9ec823/panic-itm-0.4.2/src/lib.rs","byte_start":507,"byte_end":519,"line_start":19,"line_end":19,"column_start":1,"column_end":13}},{"value":"/ (gdb) monitor tpiu config external uart off 8000000 2000000","span":{"file_name":"/home/d33p/.cargo/registry/src/github.com-1ecc6299db9ec823/panic-itm-0.4.2/src/lib.rs","byte_start":520,"byte_end":583,"line_start":20,"line_end":20,"column_start":1,"column_end":64}},{"value":"/ (gdb) monitor itm port 0 on","span":{"file_name":"/home/d33p/.cargo/registry/src/github.com-1ecc6299db9ec823/panic-itm-0.4.2/src/lib.rs","byte_start":584,"byte_end":615,"line_start":21,"line_end":21,"column_start":1,"column_end":32}},{"value":"/ (gdb) continue","span":{"file_name":"/home/d33p/.cargo/registry/src/github.com-1ecc6299db9ec823/panic-itm-0.4.2/src/lib.rs","byte_start":616,"byte_end":634,"line_start":22,"line_end":22,"column_start":1,"column_end":19}},{"value":"/ (..)","span":{"file_name":"/home/d33p/.cargo/registry/src/github.com-1ecc6299db9ec823/panic-itm-0.4.2/src/lib.rs","byte_start":635,"byte_end":643,"line_start":23,"line_end":23,"column_start":1,"column_end":9}},{"value":"/ ```","span":{"file_name":"/home/d33p/.cargo/registry/src/github.com-1ecc6299db9ec823/panic-itm-0.4.2/src/lib.rs","byte_start":644,"byte_end":651,"line_start":24,"line_end":24,"column_start":1,"column_end":8}},{"value":"/","span":{"file_name":"/home/d33p/.cargo/registry/src/github.com-1ecc6299db9ec823/panic-itm-0.4.2/src/lib.rs","byte_start":652,"byte_end":655,"line_start":25,"line_end":25,"column_start":1,"column_end":4}},{"value":"/ ``` text","span":{"file_name":"/home/d33p/.cargo/registry/src/github.com-1ecc6299db9ec823/panic-itm-0.4.2/src/lib.rs","byte_start":656,"byte_end":668,"line_start":26,"line_end":26,"column_start":1,"column_end":13}},{"value":"/ $ itmdump -f /dev/ttyUSB0","span":{"file_name":"/home/d33p/.cargo/registry/src/github.com-1ecc6299db9ec823/panic-itm-0.4.2/src/lib.rs","byte_start":669,"byte_end":698,"line_start":27,"line_end":27,"column_start":1,"column_end":30}},{"value":"/ panicked at 'FOO', src/main.rs:6:5","span":{"file_name":"/home/d33p/.cargo/registry/src/github.com-1ecc6299db9ec823/panic-itm-0.4.2/src/lib.rs","byte_start":699,"byte_end":737,"line_start":28,"line_end":28,"column_start":1,"column_end":39}},{"value":"/ ```","span":{"file_name":"/home/d33p/.cargo/registry/src/github.com-1ecc6299db9ec823/panic-itm-0.4.2/src/lib.rs","byte_start":738,"byte_end":745,"line_start":29,"line_end":29,"column_start":1,"column_end":8}},{"value":"cfg(all(target_arch = \"arm\", target_os = \"none\"))","span":{"file_name":"/home/d33p/.cargo/registry/src/github.com-1ecc6299db9ec823/panic-itm-0.4.2/src/lib.rs","byte_start":747,"byte_end":800,"line_start":31,"line_end":31,"column_start":1,"column_end":54}},{"value":"deny(missing_docs)","span":{"file_name":"/home/d33p/.cargo/registry/src/github.com-1ecc6299db9ec823/panic-itm-0.4.2/src/lib.rs","byte_start":801,"byte_end":823,"line_start":32,"line_end":32,"column_start":1,"column_end":23}},{"value":"deny(warnings)","span":{"file_name":"/home/d33p/.cargo/registry/src/github.com-1ecc6299db9ec823/panic-itm-0.4.2/src/lib.rs","byte_start":824,"byte_end":842,"line_start":33,"line_end":33,"column_start":1,"column_end":19}},{"value":"no_std","span":{"file_name":"/home/d33p/.cargo/registry/src/github.com-1ecc6299db9ec823/panic-itm-0.4.2/src/lib.rs","byte_start":843,"byte_end":853,"line_start":34,"line_end":34,"column_start":1,"column_end":11}}]}],"impls":[],"refs":[],"macro_refs":[],"relations":[]}